Metadata-Version: 1.0
Name: xgbert
Version: 0.0.1
Summary: sherbert
Home-page: https://github.com/alvations/xgbert
Author: UNKNOWN
Author-email: UNKNOWN
License: UNKNOWN
Platform: UNKNOWN
